api_mimic/__init__.py
api_mimic/compat.py
api_mimic/factories.py
api_mimic/factories.pyi
api_mimic-1.0b3.dist-info/DESCRIPTION.rst
api_mimic-1.0b3.dist-info/METADATA
api_mimic-1.0b3.dist-info/RECORD
api_mimic-1.0b3.dist-info/WHEEL
api_mimic-1.0b3.dist-info/metadata.json
api_mimic-1.0b3.dist-info/top_level.txt
